{
  "openapi": "3.0.1",
  "info": {
    "title": "AuthService.API",
    "version": "1.0"
  },
  "paths": {
    "/Account/Register": {
      "post": {
        "tags": [
          "Account"
        ],
        "requestBody": {
          "content": {
            "application/json": {
              "schema": {
                "$ref": "#/components/schemas/RegisterUserCommand"
              }
            },
            "text/json": {
              "schema": {
                "$ref": "#/components/schemas/RegisterUserCommand"
              }
            },
            "application/*+json": {
              "schema": {
                "$ref": "#/components/schemas/RegisterUserCommand"
              }
            }
          }
        },
        "responses": {
          "200": {
            "description": "Success"
          }
        }
      }
    },
    "/Account/Profile": {
      "get": {
        "tags": [
          "Account"
        ],
        "responses": {
          "200": {
            "description": "Success"
          }
        }
      }
    }
  },
  "components": {
    "schemas": {
      "RegisterUserCommand": {
        "type": "object",
        "properties": {
          "email": {
            "type": "string",
            "nullable": true
          },
          "password": {
            "type": "string",
            "nullable": true
          },
          "firstName": {
            "type": "string",
            "nullable": true
          },
          "lastName": {
            "type": "string",
            "nullable": true
          }
        },
        "additionalProperties": false
      }
    }
  }
}